plotsandgraphs/__init__.py
plotsandgraphs/binary_classifier.py
plotsandgraphs/compare_distributions.py
plotsandgraphs/multiclass_classifier.py
plotsandgraphs/pipeline.py
plotsandgraphs/utils.py
plotsandgraphs-0.1.4.dist-info/LICENSE
plotsandgraphs-0.1.4.dist-info/METADATA
plotsandgraphs-0.1.4.dist-info/WHEEL
plotsandgraphs-0.1.4.dist-info/entry_points.txt
plotsandgraphs-0.1.4.dist-info/top_level.txt
plotsandgraphs-0.1.4.dist-info/RECORD
